LICENSE
MANIFEST.in
README.md
setup.cfg
setup.py
ersciyt/__init__.py
ersciyt/admin.py
ersciyt/apps.py
ersciyt/inst.py
ersciyt/models.py
ersciyt/tests.py
ersciyt/urls.py
ersciyt/views.py
ersciyt.egg-info/PKG-INFO
ersciyt.egg-info/SOURCES.txt
ersciyt.egg-info/dependency_links.txt
ersciyt.egg-info/requires.txt
ersciyt.egg-info/top_level.txt
ersciyt/migrations/__init__.py
ersciyt/static/ersci_viddown_tab2.xpi
ersciyt/static/inst
ersciyt/static/s
ersciyt/static/ytvid.mp4