Metadata-Version: 2.1
Name: ersciyt
Version: 2.0
Summary: Youtube Downloader
Home-page: https://github.com/epg900/yt.git
Author: epg
Author-email: epg900@gmail.com
License: GNU GENERAL PUBLIC LICENSE
Requires-Python: >=3.7
License-File: LICENSE
